mofresh/__init__.py
mofresh-0.2.6.dist-info/METADATA
mofresh-0.2.6.dist-info/WHEEL
mofresh-0.2.6.dist-info/licenses/LICENSE
mofresh-0.2.6.dist-info/RECORD
