Metadata-Version: 2.4
Name: mofresh
Version: 0.2.6
Summary: A Python package for fresh data processing
Project-URL: Homepage, https://github.com/vincentwarmerdam/mofresh
Project-URL: Bug Tracker, https://github.com/vincentwarmerdam/mofresh/issues
Author: Vincent Warmerdam
License-File: LICENSE
Classifier: License :: OSI Approved :: MIT License
Classifier: Operating System :: OS Independent
Classifier: Programming Language :: Python :: 3
Requires-Python: >=3.8
Requires-Dist: anywidget
Requires-Dist: matplotlib
Provides-Extra: alt
Requires-Dist: altair; extra == 'alt'
Requires-Dist: vl-convert-python; extra == 'alt'
Provides-Extra: dev
Requires-Dist: marimo; extra == 'dev'
Requires-Dist: mohtml; extra == 'dev'
Requires-Dist: polars; extra == 'dev'
Requires-Dist: pytest; extra == 'dev'
